Workbook
Name Display_Week: 'Project Schedule'!$E$4
Name Project_Start: 'Project Schedule'!$E$3
Name task_end: 'Project Schedule'!$F1
Name task_progress: 'Project Schedule'!$D1
Name task_start: 'Project Schedule'!$E1
Name today: TODAY()

Sheet Dashboards
C30: Bottom Up | F30: Top Down | I30: ARR Target
C31: Based on how much we think we can charge for our product (i.e., premium subscription at $300k per year for enterprise and $150k per year for SME) | F31: Number of singapore-sized markets needed to reach revenue goals based on different market penetration rates of SAM (i.e., baseline case = market penetration rate of 10%)
B32: Year | C32: Revenue | D32: Cost | E32: [Team member] | F32: Baseline Case | G32: Worst Case | H32: Best Case
B33: 2022 | C33: ='Cash Flow Summary (Bottom-Up)'!H4 -> 0 | D33: 0 | E33: 0 | F33: - | G33: - | H33: -
B34: =B33+1 -> 2023 | C34: ='Cash Flow Summary (Bottom-Up)'!H5 -> 1125000 | D34: 300000 | E34: =-D34+C34 -> 825000 | F34: =C34/'Market Sizing (Top Down)'!$H$12 -> 0.47745358 | G34: =C34/'Market Sizing (Top Down)'!$H$13 -> 0.95490716 | H34: =C34/'Market Sizing (Top Down)'!$H$14 -> 0.23872679 | I34: $1M ARR | J34: Year 1
B35: =B34+1 -> 2024 | C35: ='Cash Flow Summary (Bottom-Up)'!H6 -> 3375000 | D35: 1200000 | E35: =E34+C35-D35 -> 3000000 | F35: =C35/'Market Sizing (Top Down)'!$H$12 -> 1.4323607 | G35: =C35/'Market Sizing (Top Down)'!$H$13 -> 2.8647215 | H35: =C35/'Market Sizing (Top Down)'!$H$14 -> 0.71618037 | I35: $3M ARR | J35: Year 2
B36: =B35+1 -> 2025 | C36: ='Cash Flow Summary (Bottom-Up)'!H7 -> 10125000 | D36: 2500000 | E36: =E35+C36-D36 -> 10625000 | F36: =C36/'Market Sizing (Top Down)'!$H$12 -> 4.2970822 | G36: =C36/'Market Sizing (Top Down)'!$H$13 -> 8.5941645 | H36: =C36/'Market Sizing (Top Down)'!$H$14 -> 2.1485411 | I36: $9M ARR | J36: Year 3
B37: =B36+1 -> 2026 | C37: ='Cash Flow Summary (Bottom-Up)'!H8 -> 26250000 | D37: 12000000 | E37: =E36+C37-D37 -> 24875000 | F37: =C37/'Market Sizing (Top Down)'!$H$12 -> 11.140584 | G37: =C37/'Market Sizing (Top Down)'!$H$13 -> 22.281167 | H37: =C37/'Market Sizing (Top Down)'!$H$14 -> 5.5702918 | I37: $20M ARR | J37: Year 4
B38: =B37+1 -> 2027 | C38: ='Cash Flow Summary (Bottom-Up)'!H9 -> 48750000 | D38: 18000000 | E38: =E37+C38-D38 -> 55625000 | F38: =C38/'Market Sizing (Top Down)'!$H$12 -> 20.689655 | G38: =C38/'Market Sizing (Top Down)'!$H$13 -> 41.37931 | H38: =C38/'Market Sizing (Top Down)'!$H$14 -> 10.344828 | I38: $50M ARR | J38: Year 5
B39: =B38+1 -> 2028 | C39: ='Cash Flow Summary (Bottom-Up)'!H10 -> 97500000 | D39: 22000000 | E39: =E38+C39-D39 -> 131125000 | F39: =C39/'Market Sizing (Top Down)'!$H$12 -> 41.37931 | G39: =C39/'Market Sizing (Top Down)'!$H$13 -> 82.758621 | H39: =C39/'Market Sizing (Top Down)'!$H$14 -> 20.689655 | I39: $100M ARR | J39: Year 6

Sheet Cash Flow Summary (Bottom-Up)
I2: Product 1 | K2: Product 2 | M2: Product 3
B3: Year | C3: Revenue | D3: Cost | E3: [Team member] | G3: Year | H3: Revenue | I3: Users | J3: Revenues | K3: Users | L3: Revenues | M3: Users | N3: Revenues | P3: ARR Target
B4: 2022 | C4: =H4 -> 0 | D4: 0 | E4: 0 | G4: 2022 | H4: =J4+L4+N4 -> 0 | I4: 1 | J4: =I4*$J$13 -> 0 | K4: 0 | L4: =K4*$J$14 -> 0 | M4: 0 | N4: =M4*$J$15 -> 0
B5: =B4+1 -> 2023 | C5: =H5 -> 1125000 | D5: 300000 | E5: =-D5+C5 -> 825000 | G5: =G4+1 -> 2023 | H5: =J5+L5+N5 -> 1125000 | I5: 10 | J5: =I5*$J$13 -> 0 | K5: 3 | L5: =K5*$J$14 -> 225000 | M5: 3 | N5: =M5*$J$15 -> 900000 | P5: $1M ARR
B6: =B5+1 -> 2024 | C6: =H6 -> 3375000 | D6: 1200000 | E6: =E5+C6-D6 -> 3000000 | G6: =G5+1 -> 2024 | H6: =J6+L6+N6 -> 3375000 | I6: 20 | J6: =I6*$J$13 -> 0 | K6: 9 | L6: =K6*$J$14 -> 675000 | M6: 9 | N6: =M6*$J$15 -> 2700000 | P6: $3M ARR
B7: =B6+1 -> 2025 | C7: =H7 -> 10125000 | D7: 2500000 | E7: =E6+C7-D7 -> 10625000 | G7: =G6+1 -> 2025 | H7: =J7+L7+N7 -> 10125000 | I7: 40 | J7: =I7*$J$13 -> 0 | K7: 27 | L7: =K7*$J$14 -> 2025000 | M7: 27 | N7: =M7*$J$15 -> 8100000 | P7: $9M ARR
B8: =B7+1 -> 2026 | C8: =H8 -> 26250000 | D8: 12000000 | E8: =E7+C8-D8 -> 24875000 | G8: =G7+1 -> 2026 | H8: =J8+L8+N8 -> 26250000 | I8: 80 | J8: =I8*$J$13 -> 0 | K8: 70 | L8: =K8*$J$14 -> 5250000 | M8: 70 | N8: =M8*$J$15 -> 21000000 | P8: $20M ARR
B9: =B8+1 -> 2027 | C9: =H9 -> 48750000 | D9: 18000000 | E9: =E8+C9-D9 -> 55625000 | G9: =G8+1 -> 2027 | H9: =J9+L9+N9 -> 48750000 | I9: 160 | J9: =I9*$J$13 -> 0 | K9: 130 | L9: =K9*$J$14 -> 9750000 | M9: 130 | N9: =M9*$J$15 -> 39000000 | P9: $50M ARR
B10: =B9+1 -> 2028 | C10: =H10 -> 97500000 | D10: 22000000 | E10: =E9+C10-D10 -> 131125000 | G10: =G9+1 -> 2028 | H10: =J10+L10+N10 -> 97500000 | I10: 320 | J10: =I10*$J$13 -> 0 | K10: 260 | L10: =K10*$J$14 -> 19500000 | M10: 260 | N10: =M10*$J$15 -> 78000000 | P10: $100M ARR
H12: Offering | I12: Description | J12: Estimated Pricing (Annual)
H13: Product 1 | I13: Open Source (Free) | J13: 0
H14: Product 2 | I14: SME | J14: 75000
H15: Product 3 | I15: Enterprise | J15: 300000

Sheet Market Sizing (Top Down)
C2: Singapore
D4: Vertical Farming | E4: ?? Maybe a Hospital or a Retail Store | F4: Developers | G4: REITs
B5: A | C5: Number of Businesses | D5: 25 | E5: ?? | F5: 75 | G5: 40
B6: B | C6: Annual Revenues (Average) | D6: =5*10^5 -> 500000 | E6: =5*10^6 -> 5000000 | F6: =500*10^6 -> 500000000 | G6: =50*10^6 -> 50000000
B7: C | C7: Estimated Expense % (Operating) | D7: 0.5 | F7: 0.98 | G7: 0.2
B8: D | C8: Estimated Income (Revenues - Expenses) | D8: =D6*(1-D7) -> 250000 | F8: =F6*(1-F7) -> 10000000 | G8: =G6*(1-G7) -> 40000000
B9: E | C9: Estimated Budget for Tech (1 % of Income) | D9: =D8*0.01 -> 2500 | F9: =F8*0.01 -> 100000 | G9: =G8*0.01 -> 400000
B11: F | C11: Servicable Available Market (SAM) (A * E) | D11: =D5*D9 -> 62500 | F11: =F5*F9 -> 7500000 | G11: =G5*G9 -> 16000000 | H11: =SUM(D11:G11) -> 23562500 | I11: SAM
B12: G | C12: Serviceable Obtainable Market (SOM) - Base Case (F * 10%) | D12: =D11*0.1 -> 6250 | F12: =F11*0.1 -> 750000 | G12: =G11*0.1 -> 1600000 | H12: =SUM(D12:G12) -> 2356250 | I12: Base Case
B13: H | C13: Serviceable Obtainable Market (SOM) - Worst Case (F * 5%) | D13: =D11*0.05 -> 3125 | F13: =F11*0.05 -> 375000 | G13: =G11*0.05 -> 800000 | H13: =SUM(D13:G13) -> 1178125 | I13: Worst Case
B14: I | C14: Serviceable Obtainable Market (SOM) - Best Case (F * 20%) | D14: =D11*0.2 -> 12500 | F14: =F11*0.2 -> 1500000 | G14: =G11*0.2 -> 3200000 | H14: =SUM(D14:G14) -> 4712500 | I14: Best Case

Sheet Product Costing
B2: Man-hours Needed
C4: Solution Components
C5: Platform (Data Engineering) | D5: Function | E5: Model
B6: Technical Lead
B7: Data Scientist
B8: Data Analyst
B9: Data Engineer
B10: Developer - Senior
B11: Developer - Junior

Sheet Project Schedule
A1: Create a Project Schedule in this worksheet. Enter title of this project in cell B1. Information about how to use this worksheet, including instructions for screen readers and the author of this workbook is in the About worksheet. Continue navigating down column A to hear further instructions. | B1: BEAMP Project Timeline
A2: Enter Company Name in cell B2. | B2: Ambient Systems
A3: Enter the name of the Project Lead in cell B3. Enter the Project Start date in cell E3. Project Start: label is in cell C3. | B3: Ivan Damnjanovic | C3: Project Start: | E3: 44581
A4: The Display Week in cell E4 represents the starting week to display in the project schedule in cell I4. The project start date is considered Week 1. To change the display week, simply enter a new week number in cell E4. The starting date for each week, starting with the display week from cell E4, starts in cell I4 and is auto calculated. There are 8 weeks represented in this view from cell I4 through cell BF4. You should not modify these cells. Display Week: label is in cell C4. | C4: Display Week: | E4: 1 | I4: =I5 -> 44578 | P4: =P5 -> 44585 | W4: =W5 -> 44592 | AD4: =AD5 -> 44599 | AK4: =AK5 -> 44606 | AR4: =AR5 -> 44613 | AY4: =AY5 -> 44620 | BF4: =BF5 -> 44627
A5: Cells I5 through BL5 contain the day number for the week represented in the cell block above each date cell and are auto calculated. You should not modify these cells. Today's date is outlined in Red (hex #AD3815) from today's date in row 5 through the entire date column to the end of the project schedule. | I5: =Project_Start-WEEKDAY(Project_Start,1)+2+7*(Display_Week-1) -> 44578 | J5: =I5+1 -> 44579 | K5: =J5+1 -> 44580 | L5: =K5+1 -> 44581 | M5: =L5+1 -> 44582 | N5: =M5+1 -> 44583 | O5: =N5+1 -> 44584 | P5: =O5+1 -> 44585 | Q5: =P5+1 -> 44586 | ... BL5: =BK5+1 -> 44633
A6: This row contains headers for the project schedule that follows below them. Navigate from B6 through BL 6 to hear the content. The first letter of each day of the week for the date above that heading, starts in cell I6 and continues through cell BL6. All project timeline charting is auto generated based on the start and end dates entered, using conditional formats. Do not modify content in cells within columns after column I starting with cell I7. | B6: TASK | C6: ASSIGNED TO | D6: PROGRESS | E6: START | F6: END | H6: DAYS | I6: =LEFT(TEXT(I5,"ddd"),1) -> M | J6: =LEFT(TEXT(J5,"ddd"),1) -> T | K6: =LEFT(TEXT(K5,"ddd"),1) -> W | L6: =LEFT(TEXT(L5,"ddd"),1) -> T | M6: =LEFT(TEXT(M5,"ddd"),1) -> F | N6: =LEFT(TEXT(N5,"ddd"),1) -> S | O6: =LEFT(TEXT(O5,"ddd"),1) -> S | P6: =LEFT(TEXT(P5,"ddd"),1) -> M | ... BL6: =LEFT(TEXT(BL5,"ddd"),1) -> S
A7: Do not delete this row. This row is hidden to preserve a formula that is used to highlight the current day within the project schedule. | H7: =IF(OR(ISBLANK(task_start),ISBLANK(task_end)),"",task_end-task_start+1)
A8: Cell B8 contains the Phase 1 sample title. Enter a new Title in cell B8. Enter a name to assign the phase to, if it applies for your project, in cell C8. [Team member] for the entire phase, if it applies for your project, in cell D8. Enter the start and end dates for the entire phase, if it applies for your project, in cells E8 and F8. The Gantt chart will automatically fill in the appropriate dates and shade according to the progress entered. To delete the phase and work only from tasks, simply delete this row. | B8: User Studies & Feedback Collection | H8: =IF(OR(ISBLANK(task_start),ISBLANK(task_end)),"",task_end-task_start+1)
A9: Cell B9 contains the sample task "Task 1." Enter a new task name in cell B9. Enter a person to assign the task to in cell C9. Enter progress of the task in cell D9. A progress bar appears in the cell and is shaded according to the number in the cell. For example, 50 percent progress would shade half of the cell. Enter task start date in cell E9. Enter task end date in cell F9. A status bar shaded for the dates entered appears in blocks starting from cell I9 through BL9. | B9: Task 1 | C9: Name | D9: 0.5 | E9: =Project_Start -> 44581 | F9: =E9+3 -> 44584 | H9: =IF(OR(ISBLANK(task_start),ISBLANK(task_end)),"",task_end-task_start+1) -> 4
A10: Rows 10 through 13 repeat the pattern from row 9. Repeat the instructions from cell A9 for all task rows in this worksheet. Overwrite any sample data. A sample of another phase starts in cell A14. Continue entering tasks in cells A10 through A13 or go to cell A14 to learn more. | B10: Task 2 | D10: 0.6 | E10: =F9 -> 44584 | F10: =E10+2 -> 44586 | H10: =IF(OR(ISBLANK(task_start),ISBLANK(task_end)),"",task_end-task_start+1) -> 3
B11: Task 3 | D11: 0.5 | E11: =F10 -> 44586 | F11: =E11+4 -> 44590 | H11: =IF(OR(ISBLANK(task_start),ISBLANK(task_end)),"",task_end-task_start+1) -> 5
B12: Task 4 | D12: 0.25 | E12: =F11 -> 44590 | F12: =E12+5 -> 44595 | H12: =IF(OR(ISBLANK(task_start),ISBLANK(task_end)),"",task_end-task_start+1) -> 6
B13: Task 5 | E13: =E10+1 -> 44585 | F13: =E13+2 -> 44587 | H13: =IF(OR(ISBLANK(task_start),ISBLANK(task_end)),"",task_end-task_start+1) -> 3
A14: The cell at right contains the Phase 2 sample title. You can create a new phase at any time within column B. This project schedule does not require phases. To remove the phase, simply delete the row. To create a new phase block in this row, enter a new Title in cell at right. To continue adding tasks to the phase above, enter a new row above this one and fill in the task data as in cell A9's instruction. Update the Phase details in cell at right based on cell A8's instruction. Continue navigating down column A cells to learn more. If you haven't added any new rows in this worksheet, you will find 2 additional sample phase blocks have been created for you in cells B20 and B26. Otherwise, navigate through column A cells to find the additional blocks. Repeat the instructions from cells A8 and A9 whenever you need to. | B14: Phase 2 Title | H14: =IF(OR(ISBLANK(task_start),ISBLANK(task_end)),"",task_end-task_start+1)
B15: Task 1 | D15: 0.5 | E15: =E13+1 -> 44586 | F15: =E15+4 -> 44590 | H15: =IF(OR(ISBLANK(task_start),ISBLANK(task_end)),"",task_end-task_start+1) -> 5
B16: Task 2 | D16: 0.5 | E16: =E15+2 -> 44588 | F16: =E16+5 -> 44593 | H16: =IF(OR(ISBLANK(task_start),ISBLANK(task_end)),"",task_end-task_start+1) -> 6
B17: Task 3 | E17: =F16 -> 44593 | F17: =E17+3 -> 44596 | H17: =IF(OR(ISBLANK(task_start),ISBLANK(task_end)),"",task_end-task_start+1) -> 4
B18: Task 4 | E18: =E17 -> 44593 | F18: =E18+2 -> 44595 | H18: =IF(OR(ISBLANK(task_start),ISBLANK(task_end)),"",task_end-task_start+1) -> 3
B19: Task 5 | E19: =E18 -> 44593 | F19: =E19+3 -> 44596 | H19: =IF(OR(ISBLANK(task_start),ISBLANK(task_end)),"",task_end-task_start+1) -> 4
A20: Sample phase title block | B20: Phase 3 Title | H20: =IF(OR(ISBLANK(task_start),ISBLANK(task_end)),"",task_end-task_start+1)
B21: Task 1 | E21: =E9+15 -> 44596 | F21: =E21+5 -> 44601 | H21: =IF(OR(ISBLANK(task_start),ISBLANK(task_end)),"",task_end-task_start+1) -> 6
B22: Task 2 | E22: =F21+1 -> 44602 | F22: =E22+4 -> 44606 | H22: =IF(OR(ISBLANK(task_start),ISBLANK(task_end)),"",task_end-task_start+1) -> 5
B23: Task 3 | E23: =E22+5 -> 44607 | F23: =E23+5 -> 44612 | H23: =IF(OR(ISBLANK(task_start),ISBLANK(task_end)),"",task_end-task_start+1) -> 6
B24: Task 4 | E24: =F23+1 -> 44613 | F24: =E24+4 -> 44617 | H24: =IF(OR(ISBLANK(task_start),ISBLANK(task_end)),"",task_end-task_start+1) -> 5
B25: Task 5 | E25: =E23 -> 44607 | F25: =E25+4 -> 44611 | H25: =IF(OR(ISBLANK(task_start),ISBLANK(task_end)),"",task_end-task_start+1) -> 5
A26: Sample phase title block | B26: Phase 4 Title | H26: =IF(OR(ISBLANK(task_start),ISBLANK(task_end)),"",task_end-task_start+1)
B27: Task 1 | E27: date | F27: date | H27: =IF(OR(ISBLANK(task_start),ISBLANK(task_end)),"",task_end-task_start+1) -> #VALUE!
B28: Task 2 | E28: date | F28: date | H28: =IF(OR(ISBLANK(task_start),ISBLANK(task_end)),"",task_end-task_start+1) -> #VALUE!
B29: Task 3 | E29: date | F29: date | H29: =IF(OR(ISBLANK(task_start),ISBLANK(task_end)),"",task_end-task_start+1) -> #VALUE!
B30: Task 4 | E30: date | F30: date | H30: =IF(OR(ISBLANK(task_start),ISBLANK(task_end)),"",task_end-task_start+1) -> #VALUE!
B31: Task 5 | E31: date | F31: date | H31: =IF(OR(ISBLANK(task_start),ISBLANK(task_end)),"",task_end-task_start+1) -> #VALUE!
A32: This is an empty row | H32: =IF(OR(ISBLANK(task_start),ISBLANK(task_end)),"",task_end-task_start+1)
A33: This row marks the end of the Project Schedule. DO NOT enter anything in this row. Insert new rows ABOVE this one to continue building out your Project Schedule. | B33: Insert new rows ABOVE this one | H33: =IF(OR(ISBLANK(task_start),ISBLANK(task_end)),"",task_end-task_start+1)
